<tei>
    <teiHeader>
        <fileDesc xml:id="_715165322333.pdf"/>
    </teiHeader>
    <text xml:lang="en">


        <figure type="table">

            <figDesc>4.<lb/> Ce document présente une analyse de la relation entre désavantage social et parcours éducatifs<lb/> des individus issus d&apos;un milieu familial défavorisé à chaque étape de leur vie, et décrit certaines des<lb/> conséquences de ces parcours pour la société dans son ensemble. Une conclusion générale est que si la<lb/> formation peut servir d&apos;ascenseur social –– en offrant de meilleures perspectives d&apos;emploi aux jeunes les<lb/> plus menacés de dénuement et en réduisant la prévalence de la pauvreté économique à l&apos;âge adulte ––<lb/> l&apos;échec scolaire peut en revanche renforcer le désavantage social : dans plusieurs pays de l&apos;OCDE, une<lb/> minorité importante d&apos;élèves n&apos;arrive même pas au terme de l&apos;enseignement obligatoire ; dans le premier<lb/> cycle du secondaire, les résultats des élèves aux tests dépendent beaucoup des caractéristiques de la<lb/> famille ; et le développement des études universitaires a le plus souvent profité aux ménages dont les<lb/> parents étaient relativement mieux instruits. Loin d&apos; « égaliser » les chances, l&apos;éducation peut être un<lb/> puissant moteur de sélection sociale. Dans un contexte où le rendement de la formation augmente avec le<lb/> temps, cette dynamique pourrait conduire à une persistance de la pauvreté de génération en génération plus<lb/> accentuée ainsi qu&apos;une diminution de l&apos;égalité des chances.<lb/> 5.<lb/> Ce rapport analyse aussi le rôle des politiques qui sont plus particulièrement axées sur les<lb/> parcours d&apos;apprentissage des personnes issues des milieux défavorisés, dans le cadre d&apos;une stratégie plus<lb/> vaste de lutte contre la pauvreté et l&apos;exclusion sociale. Ces mesures peuvent être groupées dans deux<lb/> grandes catégories:<lb/> </figDesc>
<lb/> 
            <table>• Les politiques d&apos;éducation. Ces politiques peuvent être conçues dans le but de compenser<lb/> certains aspects essentiels des désavantages dus au milieu familial, qui freinent la réussite<lb/> scolaire, sans pour autant nécessairement entraver celle des meilleurs élèves. Dans certains pays<lb/> de l&apos;OCDE, les règles d&apos;admission à l&apos;école sont beaucoup plus équitables que dans d&apos;autres et la<lb/> répartition des élèves par niveau de compétence se fait à un âge ultérieur. Les mesures destinées à<lb/> renforcer les compétences à la fois cognitives et non cognitives des élèves issus des milieux<lb/> défavorisés peuvent jouer un rôle important en limitant l&apos;exclusion sociale et en atténuant le<lb/> recours à des mesures sociales à un stade ultérieur de la vie des intéressés.<lb/> • Les politiques sociales. Ces politiques peuvent dans leur conception avoir un contenu formation<lb/> plus important. Sont en l&apos;occurrence privilégiés : les politiques qui prévoient l&apos;octroi de<lb/> ressources financières aux familles à la condition que ces dernières envoient leurs enfants à<lb/> l&apos;école ; les programmes de formation ciblés sur les jeunes sortis prématurément du circuit<lb/> scolaire ordinaire ; la formation pour adultes ciblée sur les individus ayant un faible niveau<lb/> d&apos;instruction ; les politiques de validation des acquis professionnels ; ainsi que les programmes<lb/> dont l&apos;objet est de modifier l&apos;attitude des parents à l&apos;égard des études (programmes de formation<lb/> à l&apos;art d&apos;être parents, par exemple) ou qui proposent des activités extra-scolaires, pouvant exercer<lb/> une influence sur des groupes d&apos;enfants du même âge.<lb/> 6.<lb/> Un aspect essentiel des programmes axés sur les parcours d&apos;apprentissage est le stade de la vie<lb/> </table>
<lb/> 
            <head>auquel </head>
 
            <figDesc>ils sont mis en oeuvre. Au fil des ans, on a accumulé une masse considérable de données qui<lb/> témoignent de l&apos;importance de cibler les programmes sur les enfants issus des milieux défavorisés dès la<lb/> préscolarisation. Il y a moins d&apos;accord pour ce qui est des effets des programmes ciblés sur des personnes<lb/> défavorisées à un stade ultérieur de leur vie. Ce document passe en revue des données factuelles<lb/> concernant trois types de programmes : les programmes mis en oeuvre dans les établissements scolaires en<lb/> faveur des élèves défavorisés ; les aides financières et le mentorat assurés à ces élèves ; et les programmes<lb/> pour les adultes et les personnes qui ont abandonné leurs études dans le deuxième cycle du secondaire. Les<lb/> évaluations disponibles suggèrent que lorsque ces programmes sont correctement conçus, bien ciblés,<lb/> adéquatement financés et suivis grâce à des stratégies appropriées d&apos;évaluation, ils peuvent améliorer à la<lb/> fois l&apos;emploi et les perspectives de gains des personnes issues de familles démunies. </figDesc>
 
            <table>SOCIAL DISADVANTAGE<lb/> AND EDUCATION EXPERIENCES</table>
        </figure>


        <figure type="table">

            <table>0<lb/> 5<lb/> 10<lb/> 15<lb/> 20<lb/> 25<lb/> 30<lb/> 35<lb/> Engla nd<lb/> Ta iwa n<lb/> Sco tland<lb/> Hunga ry<lb/> Ge rm a ny<lb/> Ko re a<lb/> Macedo nia<lb/> S lo va k R e public<lb/> B ulga ria<lb/> United States<lb/> Lithua nia<lb/> Ireland<lb/> New Zealand<lb/> C ze c h Re public<lb/> Slo venia<lb/> M a la ys ia<lb/> S o uth Afric a<lb/> C hile<lb/> Aus tra lia<lb/> Sweden<lb/> Aus tria<lb/> Rus s ia<lb/> No rwa y<lb/> Ro mania<lb/> Greece<lb/> Is rael<lb/> S inga po re<lb/> J o rdan<lb/> Ita ly<lb/> Ne the rla nds<lb/> B e lgium (F re nc h)<lb/> Switzerland<lb/> La tvia<lb/> P hillippine s<lb/> Mo ldo va<lb/> Spain<lb/> De nm a rk<lb/> C yprus<lb/> Finland<lb/> J apan<lb/> Tha ila nd<lb/> Turke y<lb/> Iceland<lb/> Ira n<lb/> B e lgium (F le m is h)<lb/> Ho ng Ko ng<lb/> P o rtuga l<lb/> C a na da<lb/> France<lb/> C o lo m bia<lb/> Mo ro c co<lb/> Tunis ia<lb/> Indo ne s ia<lb/> Kuwa it</table>
        </figure>


        <figure type="table">

            <table>Tertiary education<lb/> %<lb/> Note. Countries are ranked, from left to right, in ascending order of the participation rates in non-formal continuous<lb/> education and training, for all levels of education, within a 12-month period.<lb/> 1. Data for Canada refer to 2002.<lb/> Source: OECD (2005), Education at a Glance, Paris.</table>
        </figure>


        <figure type="table">

            <head>Table </head>
 
            <label>1</label>

            <head>. Employment rates by educational attainment<lb/> </head>
<lb/> 
            <table>Upper secondary education<lb/> ISCED 3C<lb/> Short<lb/> ISCED 3C<lb/> Long/3B<lb/> ISCED 3A<lb/> Type B<lb/> Type A and<lb/> advanced research<lb/> programmes<lb/> Australia<lb/> x(2)<lb/> 61<lb/> a<lb/> 84<lb/> 76<lb/> x(5)<lb/> 80<lb/> 85<lb/> 73<lb/> Austria<lb/> x(2)<lb/> 55<lb/> a<lb/> 74<lb/> 72<lb/> 84<lb/> 82<lb/> 88<lb/> 72<lb/> Belgium<lb/> 36<lb/> 60<lb/> a<lb/> 69<lb/> 74<lb/> 76<lb/> 82<lb/> 85<lb/> 67<lb/> Canada<lb/> 44<lb/> 63<lb/> a<lb/> x(5)<lb/> 75<lb/> 79<lb/> 82<lb/> 82<lb/> 76<lb/> Czech Republic<lb/> 8<lb/> 45<lb/> 57.1<lb/> 75<lb/> 77<lb/> 77<lb/> 81<lb/> 87<lb/> 73<lb/> Denmark<lb/> 43<lb/> 62<lb/> 84<lb/> 81<lb/> 68<lb/> c<lb/> 85<lb/> 85<lb/> 78<lb/> Finland<lb/> 52<lb/> 68<lb/> a<lb/> a<lb/> 73<lb/> c<lb/> 83<lb/> 88<lb/> 73<lb/> France<lb/> 48<lb/> 68<lb/> a<lb/> 76<lb/> 76<lb/> 73<lb/> 85<lb/> 80<lb/> 71<lb/> Germany<lb/> 43<lb/> 51<lb/> a<lb/> 70<lb/> 54<lb/> 78<lb/> 81<lb/> 84<lb/> 69<lb/> Greece<lb/> 55<lb/> 67<lb/> 79<lb/> 78<lb/> 63<lb/> 73<lb/> 79<lb/> 83<lb/> 65<lb/> Hungary<lb/> 12<lb/> 40<lb/> a<lb/> 71<lb/> 72<lb/> 77<lb/> [89]<lb/> 83<lb/> 64<lb/> Iceland<lb/> 1<lb/> 83<lb/> 86<lb/> 89<lb/> a<lb/> 88<lb/> 93<lb/> 93<lb/> 96<lb/> 90<lb/> Ireland<lb/> 47<lb/> 67<lb/> c<lb/> a<lb/> 74<lb/> 80<lb/> 84<lb/> 87<lb/> 71<lb/> Italy<lb/> 1<lb/> 33<lb/> 61<lb/> 69<lb/> 72<lb/> 72<lb/> 78<lb/> x(8)<lb/> 82<lb/> 61<lb/> Japan<lb/> x(2)<lb/> 67<lb/> a<lb/> a<lb/> 74<lb/> a<lb/> 71<lb/> 86<lb/> 75<lb/> Korea<lb/> 64<lb/> 69<lb/> a<lb/> x(5)<lb/> 70<lb/> a<lb/> 75<lb/> 77<lb/> 71<lb/> Luxembourg<lb/> 64<lb/> 56<lb/> 64<lb/> 69<lb/> 74<lb/> 82<lb/> 81<lb/> 86<lb/> 70<lb/> Mexico<lb/> 60<lb/> 71<lb/> a<lb/> 63<lb/> a<lb/> a<lb/> 77<lb/> 82<lb/> 66<lb/> Netherlands<lb/> 1<lb/> 48<lb/> 64<lb/> x(4)<lb/> 78<lb/> 83<lb/> 79<lb/> 86<lb/> 87<lb/> 74<lb/> New Zealand<lb/> x(2)<lb/> 63<lb/> a<lb/> 85<lb/> 78<lb/> 82<lb/> 78<lb/> 84<lb/> 77<lb/> Norway<lb/> c<lb/> 65<lb/> a<lb/> 79<lb/> 79<lb/> 85<lb/> 90<lb/> 89<lb/> 80<lb/> Poland<lb/> x(2)<lb/> 38<lb/> 58<lb/> a<lb/> 65<lb/> 67<lb/> x(8)<lb/> 83<lb/> 61<lb/> Portugal<lb/> 70<lb/> 82<lb/> x(5)<lb/> x(5)<lb/> 82<lb/> x(5)<lb/> 79<lb/> 90<lb/> 75<lb/> Slovak Republic<lb/> c<lb/> 30<lb/> x(4)<lb/> 67<lb/> 75<lb/> x(5)<lb/> 82<lb/> 87<lb/> 67<lb/> S p a i n<lb/> 4 7<lb/> 6 7<lb/> 6 8<lb/> 7 3<lb/> 7 2<lb/> 7 2<lb/> 8 1<lb/> 8 2<lb/> 6 6<lb/> Sweden<lb/> 59<lb/> 74<lb/> a<lb/> a<lb/> 81<lb/> x(5)<lb/> 83<lb/> 88<lb/> 80<lb/> Switzerland<lb/> 61<lb/> 68<lb/> 75<lb/> 83<lb/> 75<lb/> 86<lb/> 92<lb/> 88<lb/> 81<lb/> Turkey<lb/> 48<lb/> 58<lb/> a<lb/> 66<lb/> 58<lb/> a<lb/> x(8)<lb/> 75<lb/> 54<lb/> United Kingdom<lb/> 59<lb/> 54<lb/> 76<lb/> 80<lb/> 84<lb/> a<lb/> 87<lb/> 88<lb/> 78<lb/> United States<lb/> 54<lb/> 60<lb/> x(5)<lb/> x(5)<lb/> 73<lb/> x(5)<lb/> 79<lb/> 83<lb/> 75<lb/> A v e r a g e<lb/> 4 9<lb/> 6 1<lb/> 7 2<lb/> 7 5<lb/> 7 4<lb/> 7 9<lb/> 8 2<lb/> 8 5<lb/> 7 2<lb/> Tertiary education<lb/> All levels of<lb/> education<lb/> Pre-primary and<lb/> primary<lb/> education<lb/> Lower<lb/> secondary<lb/> education<lb/> Post-secondary<lb/> non-tertiary<lb/> education</table>
        </figure>


        <figure type="table">

            <head>table </head>
 
            <label>(</label>

            <head>e</head>

            <table>.g., x(2) means that data are included in the second column<lb/> of the table.<lb/> 1. Data for the Netherlands refer to 2002.<lb/> Source: OECD (2005), Education at a Glance, Paris.</table>
        </figure>


        <figure type="table">

            <head>Table </head>
 
            <label>2</label>

            <head>. Evidence on the causal impact of education on earnings<lb/> </head>
<lb/> 
            <table>Study<lb/> Data<lb/> Basic<lb/> Return<lb/> Causal<lb/> Return<lb/> Means to Generate Causal Estimate<lb/> Angrist and Krueger<lb/> (1991)<lb/> US Census<lb/> 5-7%<lb/> 6-11%<lb/> Variations in years of education generated by<lb/> different quarter of birth<lb/> Card (1995)<lb/> 1966 Cohort of Young<lb/> Men, United States<lb/> 7%<lb/> 13%<lb/> Variation in years of education from proximity to<lb/> college when growing up<lb/> Conneely and<lb/> Uusitalo (1997)<lb/> Finnish men in the army<lb/> in 1982<lb/> 8%<lb/> 11%<lb/> Variation in years of education from proximity to<lb/> college when growing up<lb/> Harmon and Walker<lb/> (1995)<lb/> Family Expenditure<lb/> Survey, United Kingdom<lb/> 6%<lb/> 15%<lb/> Variation in education induced by raising of<lb/> compulsory school leaving age<lb/> Ashenfelter and<lb/> Rouse (1998)<lb/> 1991-93 Princeton<lb/> Twins Survey<lb/> 7%<lb/> 9%<lb/> Variation in education within twin pairs<lb/> Miller at al (1995)<lb/> Australian Twins<lb/> Register<lb/> 3%<lb/> 5%<lb/> Variation in education within twin pairs<lb/> Note: Examples taken from Card&apos;s (1999) review.</table>
        </figure>


        <figure type="table">

            <head>look at cohort data from the British National Child Development Study (NCDS) 4<lb/> </head>
<lb/> 
            <table>3.<lb/> For example, 22% of 16-25 year olds in Britain have literacy levels below IALS Level 2, compared to 19% of<lb/> 36-45 year olds; comparable numbers for the United States are 26% for 16-25 year olds and 18% for 36-45<lb/> year olds. In Sweden 5% of 16-25 year olds are below Level 2, and in Germany the corresponding number is<lb/> 4%. The same pattern is true of numeracy skills. See OECD (1995).<lb/> 4.<lb/> NCDS is a birth cohort surveying all people born in a week of March 1958 at various ages (7, 11, 16 23, 33<lb/> and 42 at the time of writing).</table>
        </figure>


        <figure type="table">

            <head>Table </head>
 
            <label>3</label>

            <head>. International estimates of intergenerational income mobility<lb/> </head>
<lb/> 
            <table>Country<lb/> Sons Born<lb/> Partial Correlation<lb/> United States<lb/> 1954-1970<lb/> .348<lb/> 3<lb/> United Kingdom<lb/> 1958<lb/> .260<lb/> 1<lb/> West Germany<lb/> 1960-73<lb/> .180<lb/> 3<lb/> Finland<lb/> 1958-1960<lb/> .147<lb/> 1<lb/> Sweden<lb/> 1962<lb/> .143<lb/> 1<lb/> Denmark<lb/> 1960-1973<lb/> .143<lb/> 1<lb/> Norway<lb/> 1958<lb/> .139<lb/> 1<lb/> Source:<lb/> . Bjorklund et al. (2005), Table 3; Blanden (2005), Table 3.3; Blanden, Gregg and Machin (2005b).</table>
        </figure>


        <figure type="table">

            <head>United<lb/> Kingdom (2005)<lb/> PENSIONS AT A GLANCE: Public policies across OECD countries (2005)<lb/> EXTENDING OPPORTUNITIES – How active social policy can benefit us all (2005)<lb/> SOCIETY AT A GLANCE: OECD Social Indicators (2005)<lb/> OECD EMPLOYMENT OUTLOOK (2005)<lb/> AGEING AND EMPLOYMENT POLICIES: AUSTRALIA (2005)<lb/> AGEING AND EMPLOYMENT POLICIES: AUSTRIA (2005)<lb/> AGEING AND EMPLOYMENT POLICIES: CANADA (2005)<lb/> AGEING AND EMPLOYMENT POLICIES: DENMARK (2005)<lb/> AGEING AND EMPLOYMENT POLICIES: FRANCE (2005)<lb/> AGEING AND EMPLOYMENT POLICIES: GERMANY (2005)<lb/> AGEING AND EMPLOYMENT POLICIES: NETHERLANDS (2005)<lb/> AGEING AND EMPLOYMENT POLICIES: UNITED STATES (2005)<lb/> PROMOTING ADULT LEARNING (2005)<lb/> MIGRATION, REMITTANCES AND DEVELOPMENT (2005)<lb/> TRENDS IN INTERNATIONAL MIGRATION: SOPEMI (2004)<lb/> MIGRATION FOR EMPLOYMENT: BILATERAL AGREEMENTS AT A CROSSROADS (2004)<lb/> INCOME DISPARITIES IN CHINA: AN OECD PERSPECTIVE (2004)<lb/> BENEFITS AND WAGES: OECD Indicators (2004)<lb/> REFORMING PUBLIC PENSIONS: SHARING THE EXPERIENCES OF TRANSITION AND OECD COUNTRIES<lb/> (2004)<lb/> BABIES AND BOSSES: Reconciling Work and Family Life, Volume 3, New Zealand, Portugal, Switzerland (2004)<lb/> ASSET BUILDING AND THE ESCAPE FROM POVERTY: A NEW WELFARE POLICY DEBATE (2003)<lb/> MANAGING DECENTRALISATION: A NEW ROLE FOR LABOUR MARKET POLICY (2003)<lb/> COMBATING CHILD LABOUR: A REVIEW OF POLICIES (2003)</head>
        </figure>



    </text>
</tei>

